dorado/scheduling/__init__.py
dorado/scheduling/_slew.py
dorado/scheduling/constraints/__init__.py
dorado/scheduling/constraints/bright_earth_limb.py
dorado/scheduling/constraints/earth_limb.py
dorado/scheduling/constraints/orbit_night.py
dorado/scheduling/constraints/radiation.py
dorado/scheduling/data/README.md
dorado/scheduling/data/__init__.py
dorado/scheduling/data/dorado-510km-31inc.tle
dorado/scheduling/data/dorado-510km-60inc.tle
dorado/scheduling/data/dorado-510km-sunsync.tle
dorado/scheduling/data/dorado-625km-31inc.tle
dorado/scheduling/data/dorado-625km-60inc.tle
dorado/scheduling/data/dorado-625km-sunsync.tle
dorado/scheduling/data/goes17.tle
dorado/scheduling/dust.py
dorado/scheduling/fov.py
dorado/scheduling/metrics/__init__.py
dorado/scheduling/metrics/kne.py
dorado/scheduling/mission.py
dorado/scheduling/orbit/__init__.py
dorado/scheduling/orbit/base.py
dorado/scheduling/orbit/spice.py
dorado/scheduling/orbit/tle.py
dorado/scheduling/schedulers/__init__.py
dorado/scheduling/schedulers/continuous_time_slew.py
dorado/scheduling/schedulers/discrete_time.py
dorado/scheduling/scripts/__init__.py
dorado/scheduling/scripts/animate.py
dorado/scheduling/scripts/animate_skymaps.py
dorado/scheduling/scripts/animate_survey.py
dorado/scheduling/scripts/main.py
dorado/scheduling/scripts/metrics.py
dorado/scheduling/scripts/simsurvey.py
dorado/scheduling/scripts/skygrid.py
dorado/scheduling/scripts/survey_slicer.py
dorado/scheduling/skygrid/__init__.py
dorado/scheduling/skygrid/_geodesic.py
dorado/scheduling/skygrid/_healpix.py
dorado/scheduling/skygrid/_sinusoidal.py
dorado/scheduling/skygrid/_spiral.py
dorado/scheduling/tests/__init__.py
dorado/scheduling/tests/test_earth_limb.py
dorado/scheduling/tests/test_orbit.py
dorado/scheduling/tests/test_skygrid.py
dorado/scheduling/units/__init__.py
dorado/scheduling/units/equivalencies.py
dorado/scheduling/units/orbital.py
dorado/scheduling/utils.py
dorado_scheduling-0.2.0.dist-info/LICENSE.txt
dorado_scheduling-0.2.0.dist-info/METADATA
dorado_scheduling-0.2.0.dist-info/WHEEL
dorado_scheduling-0.2.0.dist-info/entry_points.txt
dorado_scheduling-0.2.0.dist-info/RECORD
