Metadata-Version: 2.1
Name: dorado-scheduling
Version: 0.2.0
Summary: Dorado observation planning and scheduling simulations
License: NOSA
Author: Leo Singer
Author-email: leo.singer@ligo.org
Requires-Python: >=3.9,<3.12
Classifier: Development Status :: 3 - Alpha
Classifier: Intended Audience :: Science/Research
Classifier: License :: OSI Approved
Classifier: License :: Other/Proprietary License
Classifier: Programming Language :: Python :: 3
Classifier: Programming Language :: Python :: 3.9
Classifier: Programming Language :: Python :: 3.10
Classifier: Programming Language :: Python :: 3.11
Classifier: Programming Language :: Python :: 3 :: Only
Classifier: Topic :: Scientific/Engineering :: Astronomy
Provides-Extra: dev
Provides-Extra: doc
Provides-Extra: test
Requires-Dist: antiprism-python
Requires-Dist: astroplan (>=0.7)
Requires-Dist: astropy (>=4.2.1)
Requires-Dist: astropy-healpix (>=0.6)
Requires-Dist: cdshealpix
Requires-Dist: cplex
Requires-Dist: docplex
Requires-Dist: dust_extinction
Requires-Dist: dustmaps
Requires-Dist: flake8 ; extra == "dev"
Requires-Dist: gwemlightcurves
Requires-Dist: hypothesis ; extra == "test"
Requires-Dist: ipykernel ; extra == "dev"
Requires-Dist: ligo.skymap (>=1.0.0)
Requires-Dist: packaging ; extra == "doc"
Requires-Dist: pep517 ; extra == "doc"
Requires-Dist: pydata-sphinx-theme ; extra == "doc"
Requires-Dist: pytest ; extra == "test"
Requires-Dist: pytest-doctestplus ; extra == "test"
Requires-Dist: radbelt
Requires-Dist: seaborn
Requires-Dist: sgp4
Requires-Dist: shapely
Requires-Dist: skyfield ; extra == "test"
Requires-Dist: sphinx-argparse-cli ; extra == "doc"
Requires-Dist: sphinx-gallery ; extra == "doc"
Requires-Dist: spiceypy
Requires-Dist: synphot
Project-URL: Documentation, https://dorado-scheduling.readthedocs.io/
